pylitecrawler/__init__.py
pylitecrawler/crawling.py
pylitecrawler/scraping.py
pylitecrawler/status.py
pylitecrawler/utils.py
pylitecrawler-0.1.2.dist-info/licenses/LICENSE
pylitecrawler-0.1.2.dist-info/METADATA
pylitecrawler-0.1.2.dist-info/WHEEL
pylitecrawler-0.1.2.dist-info/top_level.txt
pylitecrawler-0.1.2.dist-info/RECORD
